{
"type": "FeatureCollection",
"name": "1 Lycées Collégiaux",
"crs": { "type": "name", "properties": { "name": "urn:ogc:def:crs:OGC:1.3:CRS84" } },
"features": [
{ "type": "Feature", "properties": { "fid": 120, "Commune": "Foum El Oued", "Nom établissement": "LYCEE COLLEGIAL FOUM EL OUED", "Code_établissement": "27316R", "Nombre des élèves": "49", "Fille": "46", "Garçon": "3", "Type Etablissement": "Collégial", "x": "-13.394866", "y": "27.175360" }, "geometry": { "type": "Point", "coordinates": [ -13.394866, 27.17536 ] } }
]
}
