{
"type": "FeatureCollection",
"name": "1 Ecoles Primaires",
"crs": { "type": "name", "properties": { "name": "urn:ogc:def:crs:OGC:1.3:CRS84" } },
"features": [
{ "type": "Feature", "properties": { "fid": 94, "Commune": "Dcheira", "Nom établissement": "ECOLE MÈRE DCHEIRA", "Code_établissement": "06454P", "Nombre des élèves": "24", "Fille": "11", "Garçon": "13", "Type Etablissement": "Primaire", "x": "-13.0521478652954", "y": "27.0282649993896" }, "geometry": { "type": "Point", "coordinates": [ -13.052147865295399, 27.028264999389599 ] } }
]
}
